README
setup.py
romanize/__init__.py
romanize/ara.py
romanize/arm.py
romanize/brh.py
romanize/cop.py
romanize/eng.py
romanize/fin.py
romanize/grc.py
romanize/heb.py
romanize/main.py
romanize/phn.py
romanize/romanizer.py
romanize/san.py
romanize/syc.py
romanize3.egg-info/PKG-INFO
romanize3.egg-info/SOURCES.txt
romanize3.egg-info/dependency_links.txt
romanize3.egg-info/top_level.txt