Metadata-Version: 1.1
Name: romanize3
Version: 0.1.13
Summary: Romanize - Transliteration module to romanize greek, hebrew, arabic, coptic, syriaic, phoenician, finnish, and sanskrit letters to the single roman letter equivalents and back
Home-page: https://github.com/markomanninen/romanize3
Author: Marko Manninen
Author-email: elonmedia@gmail.com
License: UNKNOWN
Download-URL: https://github.com/markomanninen/romanize3/archive/v0.1.13.tar.gz
Keywords: python,text analysis,transliteration
Platform: any
Classifier: Development Status :: 3 - Alpha
Classifier: Intended Audience :: Developers
Classifier: License :: OSI Approved :: MIT License
Classifier: Operating System :: OS Independent
Classifier: Programming Language :: Python
Classifier: Topic :: Software Development :: Libraries
